mucli/__init__.py
mucli/_case.py
mucli/_milvus.py
mucli/_option.py
mucli/main.py
mucli/pyinstaller.py
mucli-0.0.6.dist-info/METADATA
mucli-0.0.6.dist-info/WHEEL
mucli-0.0.6.dist-info/entry_points.txt
mucli-0.0.6.dist-info/RECORD
