Metadata-Version: 2.1
Name: mucli
Version: 0.0.6
Summary: Light client directly to milvus service 
Author: SimFG
Author-email: simf00544@gmail.com
Requires-Python: >=3.10,<3.13
Classifier: Programming Language :: Python :: 3
Classifier: Programming Language :: Python :: 3.10
Classifier: Programming Language :: Python :: 3.11
Classifier: Programming Language :: Python :: 3.12
Requires-Dist: click (>=8,<9)
Requires-Dist: milvus_connector (==0.1.0)
Requires-Dist: pyinstaller (>=6.5.0,<7.0.0)
Requires-Dist: python-dotenv (>=1.0.1,<2.0.0)
